computed_properties/__init__.py
computed_properties/computed_properties.py
computed_properties-0.1.2.dist-info/LICENSE
computed_properties-0.1.2.dist-info/METADATA
computed_properties-0.1.2.dist-info/WHEEL
computed_properties-0.1.2.dist-info/RECORD
