Metadata-Version: 2.3
Name: computed-properties
Version: 0.1.2
Summary: Small Python package that allows you to automatically precompute properties and recalculate them only when their dependencies change their value.
License: MIT
Author: Adrià Ciurana Lanau
Author-email: adri00796@gmail.com
Requires-Python: >=3.10,<4.0
Classifier: License :: OSI Approved :: MIT License
Classifier: Programming Language :: Python :: 3
Classifier: Programming Language :: Python :: 3.10
Classifier: Programming Language :: Python :: 3.11
Classifier: Programming Language :: Python :: 3.12
Classifier: Programming Language :: Python :: 3.13
Project-URL: Homepage, https://github.com/adriaciurana/computed-properties
Project-URL: Issues, https://github.com/adriaciurana/computed-properties/issues
